{"title":"UTS-3 My Stories for You","markdown":{"headingText":"UTS-3 My Stories for You","containsRefs":false,"markdown":"\n## Secangkir Keheningan\n\n![Secangkir Keheningan](images/secangkir-keheningan.jpg){width=95% fig-align=\"center\"}\n*Manila, 2025 — momen keheningan yang menyatukan tim di tengah kompetisi.*\n\nLangit Manila siang itu terasa sangat terik. Di ruang final Google Solution Challenge, udara dingin dari pendingin ruangan seolah tidak cukup menenangkan kepala yang dipenuhi angka, kode, dan rasa cemas. Di tengah suara keyboard dan bisik strategi tim lain, aku duduk memegang secangkir kopi yang mulai dingin. “Tenang, Rafi,” kataku pelan. “Kita hampir selesai.”  \n\nKami sudah bekerja selama dua hari penuh. Kode berjalan dengan baik, demo siap ditampilkan, tetapi suasana di antara kami terasa tegang. Salah satu rekan tim yang biasanya paling aktif tiba-tiba lebih banyak diam. Awalnya aku mengira dia hanya lelah. Aku melanjutkan latihan presentasi, menyusun kata dengan nada cepat agar terlihat percaya diri. Namun, di sela kalimatku, ia berbisik, “Aku merasa tidak didengar.”  \n\nAku menatapnya. Dalam beberapa detik, ruangan yang ramai terasa sunyi. Tak ada yang berbicara. Kami membiarkan keheningan bekerja menggantikan kata-kata. Setelah beberapa saat, aku meletakkan laptop dan berkata, “Oke, mari mulai dari awal. Menurutmu, apa yang sebetulnya ingin kita sampaikan lewat proyek ini?”  \n\nPercakapan yang muncul sesudahnya berjalan lambat, tetapi jujur. Kami saling mendengarkan, menimbang setiap kalimat dengan hati-hati. Dalam momen itulah kami menyadari, inti proyek kami bukan sekadar teknologi, melainkan kemampuan untuk benar-benar memahami orang lain.  \n\nSaat akhirnya giliran kami presentasi, tak ada lagi rasa panik. Kami berbicara sebagai satu suara. Setelah sesi selesai, salah satu juri berkata, “Your teamwork shows understanding.” Aku tersenyum kecil. Ternyata keheningan yang kami izinkan hadir justru menjadi jembatan terbaik untuk komunikasi.  \n\nSejak hari itu, aku belajar bahwa diam bukan tanda pasif. Ia adalah bentuk paling jujur dari mendengarkan. Dalam setiap percakapan, secangkir keheningan kadang menjadi alat paling ampuh untuk menemukan arah, baik dalam tim maupun dalam diri sendiri.\n\n---\n\n## Senja di Rumah Kakek\n\n![Senja di Rumah Kakek](images/senja-di-rumah-kakek.jpg){width=95% fig-align=\"center\"}\n*Amerika, 2024 — sore tenang di halaman rumah kakek yang mengajarkan arti mendengarkan dengan sabar.*\n\nSore di kota kecil itu selalu tenang. Angin berhembus pelan di antara pepohonan yang mulai meranggas, sementara matahari turun perlahan di balik perbukitan. Aku berdiri di depan rumah kakek, memandangi langit yang memudar dari biru ke jingga muda. Tidak ada suara bising, hanya dengungan lembut dari mobil yang sesekali lewat di jalan kecil beraspal. Udara dingin menyentuh kulit wajah, dan aroma rumput kering bercampur dengan wangi tanah yang lembap setelah disiram sprinkler.  \n\nKakek keluar membawa dua gelas cokelat hangat, lalu duduk di kursi goyang di sampingku. “Kau tahu,” katanya sambil menyeruput minumannya pelan, “di dunia yang sibuk, ketenangan itu jadi kemewahan.” Aku tersenyum kecil, tidak terlalu mengerti maksudnya. Kami duduk lama tanpa bicara. Biasanya aku akan sibuk memeriksa ponsel, tapi sore itu aku membiarkannya di saku. Ada sesuatu pada senja di tempat ini yang membuat waktu seolah berjalan lebih lambat.  \n\nAku menatap tangan kakek yang berkeriput, menggenggam cangkir dengan tenang. Saat akhirnya aku bertanya apa rahasianya bisa tetap damai di usia lanjut, kakek menjawab tanpa menoleh, “Karena aku berhenti mencoba memenangkan setiap percakapan.” Kalimat itu sederhana, tapi entah mengapa terasa berat. Aku terdiam cukup lama. Dalam pikiranku, terlintas berbagai momen di mana aku terlalu ingin benar, ingin menjelaskan diri sendiri, atau ingin orang lain memahami duluan. Mungkin memang benar, sebagian besar kegelisahan lahir dari keinginan untuk selalu didengar, bukan untuk benar-benar memahami.  \n\nKakek lalu tertawa kecil. “Kau tahu, dulu kakek juga keras kepala,” katanya. “Tapi waktu membuat kita belajar. Orang-orang akan lebih mudah mendengar kalau mereka merasa aman di dekatmu.” Ia menatap langit, lalu menambahkan, “Jadi, jadilah tempat yang tenang bagi orang lain.”  \n\nAku terdiam lagi, kali ini bukan karena bingung, tapi karena merasa disentuh. Aku memperhatikan burung-burung yang terbang rendah di atas halaman, membentuk pola sebelum menghilang di cakrawala. “Lihat?” kata kakek sambil menunjuk. “Mereka tahu kapan waktunya berhenti, kapan waktunya terbang lagi.”  \n\nKami tertawa pelan. Sore terus bergulir, warna jingga di langit berubah menjadi ungu muda, dan angin membawa suara bel rumah dari kejauhan. Aku ingin waktu berhenti sedikit lebih lama. Di dunia yang serba cepat, tempat seperti ini terasa langka—tempat di mana diam tidak berarti canggung, melainkan nyaman.  \n\nKetika matahari benar-benar tenggelam, kakek menepuk bahuku. “Jangan lupa,” katanya, “kadang mendengar orang lain adalah bentuk paling dalam dari berbicara.” Aku mengangguk, tidak menjawab, tapi di dadaku muncul perasaan hangat yang sulit dijelaskan.  \n\nSore itu, rumah kakek bukan hanya tempat singgah, melainkan ruang belajar sederhana tentang komunikasi yang paling tenang: berbicara sedikit, mendengarkan lebih banyak, dan membiarkan suasana berbicara lebih jujur daripada kata-kata. Di dunia yang ramai oleh suara, pelajaran itu rasanya jauh lebih berharga dari sekadar nasihat — ia seperti udara senja itu sendiri: lembut, jernih, dan menenangkan.\n\n---\n\n## Malam di Depan Kampus\n\n![Malam di Depan Kampus](images/malam-di-depan-kampus.jpg){width=95% fig-align=\"center\"}\n*Bandung, 2025 — malam yang lembap di depan kampus menjadi ruang refleksi tentang arti komunikasi yang jujur.*\n\nHujan baru saja berhenti ketika aku memarkir motor di depan kampus. Lampu jalan memantul di genangan air, membuat bayangan gedung terlihat ganda di permukaan. Udara malam terasa lembap dan dingin, menyisakan aroma tanah basah yang khas Bandung setelah hujan. Aku baru selesai rapat panjang untuk proyek kuliah, kepala masih penuh dengan daftar tugas yang menumpuk. Di tengah malam yang sepi itu, aku memilih berhenti sejenak, membiarkan mesin motor tetap hangat sambil menatap pantulan cahaya dari lampu mobil yang lewat.  \n\nTulisan besar “Bandung” di dinding depan kampus terlihat jelas, cahayanya terpantul di air. Aku memandangi huruf-huruf itu, seolah sedang memantulkan pikiranku sendiri. Kata itu terasa seperti panggilan—tempat yang menumbuhkan sekaligus menguji. Aku menarik napas panjang dan mencoba mengosongkan kepala.  \n\nAku teringat percakapan yang belum lama terjadi. Beberapa jam sebelumnya, aku sempat berselisih paham dengan teman satu tim. Kami berbeda pendapat tentang arah proyek, dan aku berbicara terlalu cepat, ingin menyelesaikan masalah dengan logika, bukan empati. Saat suasana mulai menegang, ia hanya diam, lalu berkata pelan, “Aku cuma ingin kamu mendengar dulu.” Kalimat itu sederhana tapi menohok. Aku sempat ingin membela diri, tetapi ada sesuatu dalam nada suaranya yang membuatku berhenti.  \n\nSekarang, di bawah langit malam Bandung yang lembap, kalimat itu terasa bergema kembali. Aku membuka ponsel dan menulis pesan singkat:  \n> “Maaf, aku terlalu terburu-buru tadi. Besok kita bahas lagi, pelan-pelan.”  \n\nAku menatap layar sejenak sebelum menekan tombol kirim. Setelah pesan terkirim, aku tersenyum. Rasanya seperti menutup pintu yang lama terbuka oleh ego. Kadang, memperbaiki komunikasi tidak membutuhkan teori rumit, cukup dengan keberanian untuk mengakui bahwa kita sempat salah.  \n\nBeberapa menit kemudian, aku menerima balasan:  \n> “Oke, aku juga maaf kalau tadi terlalu sensitif. Besok kita cari titik tengah, ya.”  \n\nAku membaca pesan itu berulang kali. Suasana sekitar masih sepi, hanya terdengar suara tetesan air dari pepohonan. Aku sadar, perbedaan pendapat sebenarnya bukan masalah. Yang jadi masalah adalah ketika kita terlalu sibuk membenarkan diri sampai lupa bahwa orang lain juga ingin didengar.  \n\nAku menatap lagi genangan air di depan motor. Pantulan lampu jalan membuat tulisan “Bandung” terlihat bergetar, seolah ikut bernapas bersama malam. Dalam pantulan itu, aku melihat bayangan diriku sendiri—seseorang yang sedang belajar untuk lebih sabar, lebih tulus, dan lebih sadar akan cara berbicara.  \n\nMalam di depan kampus itu mungkin tampak biasa saja bagi siapa pun yang lewat, tetapi bagiku, ia menjadi ruang kecil untuk berhenti dan belajar. Di antara sisa hujan dan udara yang dingin, aku menemukan pelajaran sederhana tentang komunikasi: bahwa jujur bukan berarti cepat, dan mendengar bukan berarti kalah. Hujan benar-benar berhenti, genangan mulai surut, dan aku menyalakan motor perlahan sambil tersenyum kecil. Aku tahu, besok aku akan berbicara dengan cara yang sedikit lebih baik—dan semoga, juga lebih mendengarkan.","srcMarkdownNoYaml":""},"formats":{"html":{"identifier":{"display-name":"HTML","target-format":"html","base-format":"html"},"execute":{"fig-width":7,"fig-height":5,"fig-format":"retina","fig-dpi":96,"df-print":"default","error":false,"eval":true,"cache":null,"freeze":false,"echo":true,"output":true,"warning":true,"include":true,"keep-md":false,"keep-ipynb":false,"ipynb":null,"enabled":null,"daemon":null,"daemon-restart":false,"debug":false,"ipynb-filters":[],"ipynb-shell-interactivity":null,"plotly-connected":true,"engine":"markdown"},"render":{"keep-tex":false,"keep-typ":false,"keep-source":false,"keep-hidden":false,"prefer-html":false,"output-divs":true,"output-ext":"html","fig-align":"default","fig-pos":null,"fig-env":null,"code-fold":"none","code-overflow":"scroll","code-link":false,"code-line-numbers":false,"code-tools":false,"tbl-colwidths":"auto","merge-includes":true,"inline-includes":false,"preserve-yaml":false,"latex-auto-mk":true,"latex-auto-install":true,"latex-clean":true,"latex-min-runs":1,"latex-max-runs":10,"latex-makeindex":"makeindex","latex-makeindex-opts":[],"latex-tlmgr-opts":[],"latex-input-paths":[],"latex-output-dir":null,"link-external-icon":false,"link-external-newwindow":false,"self-contained-math":false,"format-resources":[],"notebook-links":true},"pandoc":{"standalone":true,"wrap":"none","default-image-extension":"png","to":"html","toc":true,"output-file":"index.html"},"language":{"toc-title-document":"Table of contents","toc-title-website":"On this page","related-formats-title":"Other Formats","related-notebooks-title":"Notebooks","source-notebooks-prefix":"Source","other-links-title":"Other Links","code-links-title":"Code Links","launch-dev-container-title":"Launch Dev Container","launch-binder-title":"Launch Binder","article-notebook-label":"Article Notebook","notebook-preview-download":"Download Notebook","notebook-preview-download-src":"Download Source","notebook-preview-back":"Back to Article","manuscript-meca-bundle":"MECA Bundle","section-title-abstract":"Abstract","section-title-appendices":"Appendices","section-title-footnotes":"Footnotes","section-title-references":"References","section-title-reuse":"Reuse","section-title-copyright":"Copyright","section-title-citation":"Citation","appendix-attribution-cite-as":"For attribution, please cite this work as:","appendix-attribution-bibtex":"BibTeX citation:","appendix-view-license":"View License","title-block-author-single":"Author","title-block-author-plural":"Authors","title-block-affiliation-single":"Affiliation","title-block-affiliation-plural":"Affiliations","title-block-published":"Published","title-block-modified":"Modified","title-block-keywords":"Keywords","callout-tip-title":"Tip","callout-note-title":"Note","callout-warning-title":"Warning","callout-important-title":"Important","callout-caution-title":"Caution","code-summary":"Code","code-tools-menu-caption":"Code","code-tools-show-all-code":"Show All Code","code-tools-hide-all-code":"Hide All Code","code-tools-view-source":"View Source","code-tools-source-code":"Source Code","tools-share":"Share","tools-download":"Download","code-line":"Line","code-lines":"Lines","copy-button-tooltip":"Copy to Clipboard","copy-button-tooltip-success":"Copied!","repo-action-links-edit":"Edit this page","repo-action-links-source":"View source","repo-action-links-issue":"Report an issue","back-to-top":"Back to top","search-no-results-text":"No results","search-matching-documents-text":"matching documents","search-copy-link-title":"Copy link to search","search-hide-matches-text":"Hide additional matches","search-more-match-text":"more match in this document","search-more-matches-text":"more matches in this document","search-clear-button-title":"Clear","search-text-placeholder":"","search-detached-cancel-button-title":"Cancel","search-submit-button-title":"Submit","search-label":"Search","toggle-section":"Toggle section","toggle-sidebar":"Toggle sidebar navigation","toggle-dark-mode":"Toggle dark mode","toggle-reader-mode":"Toggle reader mode","toggle-navigation":"Toggle navigation","crossref-fig-title":"Figure","crossref-tbl-title":"Table","crossref-lst-title":"Listing","crossref-thm-title":"Theorem","crossref-lem-title":"Lemma","crossref-cor-title":"Corollary","crossref-prp-title":"Proposition","crossref-cnj-title":"Conjecture","crossref-def-title":"Definition","crossref-exm-title":"Example","crossref-exr-title":"Exercise","crossref-ch-prefix":"Chapter","crossref-apx-prefix":"Appendix","crossref-sec-prefix":"Section","crossref-eq-prefix":"Equation","crossref-lof-title":"List of Figures","crossref-lot-title":"List of Tables","crossref-lol-title":"List of Listings","environment-proof-title":"Proof","environment-remark-title":"Remark","environment-solution-title":"Solution","listing-page-order-by":"Order By","listing-page-order-by-default":"Default","listing-page-order-by-date-asc":"Oldest","listing-page-order-by-date-desc":"Newest","listing-page-order-by-number-desc":"High to Low","listing-page-order-by-number-asc":"Low to High","listing-page-field-date":"Date","listing-page-field-title":"Title","listing-page-field-description":"Description","listing-page-field-author":"Author","listing-page-field-filename":"File Name","listing-page-field-filemodified":"Modified","listing-page-field-subtitle":"Subtitle","listing-page-field-readingtime":"Reading Time","listing-page-field-wordcount":"Word Count","listing-page-field-categories":"Categories","listing-page-minutes-compact":"{0} min","listing-page-category-all":"All","listing-page-no-matches":"No matching items","listing-page-words":"{0} words","listing-page-filter":"Filter","draft":"Draft"},"metadata":{"lang":"en","fig-responsive":true,"quarto-version":"1.8.24","bibliography":["../references.bib"],"theme":"cosmo"},"extensions":{"book":{"multiFile":true}}}},"projectFormats":["html"]}